{
  "mode": "Indexed",
  "policyRule": {
    "if": {
      "allOf": [
        {
          "field": "type",
          "equals": "Microsoft.EventHub/namespaces/networkRuleSets"
        },
        {
          "field": "Microsoft.EventHub/namespaces/networkRuleSets/publicNetworkAccess",
          "notEquals": "Disabled"
        }
      ]
    },
    "then": {
      "effect": "[parameters('effect')]"
    }
  },
  "parameters": {
    "effect": {
      "type": "String",
      "metadata": {
        "displayName": "Effect",
        "description": "Enable or disable the execution of the policy"
      },
      "allowedValues": [
        "Audit",
        "Deny",
        "Disabled"
      ],
      "defaultValue": "Audit"
    }
  }
}